[{"id":1,"name":"Hally","price":"$1781.42","shipping":"$2.08","img":"http://dummyimage.com/166x100.png/dddddd/000000"},
{"id":2,"name":"Toma","price":"$1953.13","shipping":"$5.80","img":"http://dummyimage.com/203x100.png/ff4444/ffffff"},
{"id":3,"name":"Miles","price":"$2734.44","shipping":"$7.00","img":"http://dummyimage.com/242x100.png/5fa2dd/ffffff"},
{"id":4,"name":"Raf","price":"$364.41","shipping":"$2.63","img":"http://dummyimage.com/160x100.png/cc0000/ffffff"},
{"id":5,"name":"Cicily","price":"$1104.64","shipping":"$7.58","img":"http://dummyimage.com/142x100.png/ff4444/ffffff"},
{"id":6,"name":"Hamid","price":"$566.13","shipping":"$7.90","img":"http://dummyimage.com/240x100.png/cc0000/ffffff"},
{"id":7,"name":"Marcelle","price":"$1701.91","shipping":"$2.17","img":"http://dummyimage.com/152x100.png/5fa2dd/ffffff"},
{"id":8,"name":"Tyrone","price":"$695.42","shipping":"$4.85","img":"http://dummyimage.com/122x100.png/5fa2dd/ffffff"},
{"id":9,"name":"Lucretia","price":"$2247.07","shipping":"$7.34","img":"http://dummyimage.com/139x100.png/ff4444/ffffff"},
{"id":10,"name":"Franky","price":"$2125.96","shipping":"$4.45","img":"http://dummyimage.com/112x100.png/5fa2dd/ffffff"},
{"id":11,"name":"Trueman","price":"$600.29","shipping":"$7.14","img":"http://dummyimage.com/102x100.png/cc0000/ffffff"},
{"id":12,"name":"Dionne","price":"$1635.97","shipping":"$4.66","img":"http://dummyimage.com/222x100.png/dddddd/000000"},
{"id":13,"name":"Neely","price":"$1505.94","shipping":"$3.33","img":"http://dummyimage.com/211x100.png/ff4444/ffffff"},
{"id":14,"name":"Alia","price":"$2658.85","shipping":"$3.71","img":"http://dummyimage.com/216x100.png/5fa2dd/ffffff"},
{"id":15,"name":"Bran","price":"$954.21","shipping":"$5.76","img":"http://dummyimage.com/186x100.png/ff4444/ffffff"}]